{
	"configurations" : 
	[
		{
			"directories" : 
			[
				{
					"build" : ".",
					"jsonFile" : "directory-.-Debug-d0094a50bb2071803777.json",
					"minimumCMakeVersion" : 
					{
						"string" : "3.25"
					},
					"projectIndex" : 0,
					"source" : ".",
					"targetIndexes" : 
					[
						0
					]
				}
			],
			"name" : "Debug",
			"projects" : 
			[
				{
					"directoryIndexes" : 
					[
						0
					],
					"name" : "TwisterDriver",
					"targetIndexes" : 
					[
						0
					]
				}
			],
			"targets" : 
			[
				{
					"directoryIndex" : 0,
					"id" : "TwisterDriver.elf::@6890427a1f51a3e7e1df",
					"jsonFile" : "target-TwisterDriver.elf-Debug-555080ba1b9779b2777b.json",
					"name" : "TwisterDriver.elf",
					"projectIndex" : 0
				}
			]
		}
	],
	"kind" : "codemodel",
	"paths" : 
	{
		"build" : "E:/Clion_for_STM32/TwisterDriver/Software/cmake-build-debug",
		"source" : "E:/Clion_for_STM32/TwisterDriver/Software"
	},
	"version" : 
	{
		"major" : 2,
		"minor" : 4
	}
}
